pulumi_django_azure/__init__.py
pulumi_django_azure/azure_helper.py
pulumi_django_azure/context_processors.py
pulumi_django_azure/django_deployment.py
pulumi_django_azure/management/commands/__init__.py
pulumi_django_azure/management/commands/fix_cache_control.py
pulumi_django_azure/management/commands/purge_cache.py
pulumi_django_azure/management/commands/purge_cdn.py
pulumi_django_azure/management/commands/test_redis.py
pulumi_django_azure/middleware.py
pulumi_django_azure/settings.py
pulumi_django_azure-1.0.62.dist-info/METADATA
pulumi_django_azure-1.0.62.dist-info/WHEEL
pulumi_django_azure-1.0.62.dist-info/RECORD
