Metadata-Version: 2.4
Name: pulumi-django-azure
Version: 1.0.62
Summary: Simply deployment of Django on Azure with Pulumi
License-Expression: MIT
Keywords: django,pulumi,azure
Author: Maarten Ureel
Author-email: maarten@youreal.eu
Requires-Python: >=3.12,<3.15
Classifier: Programming Language :: Python
Classifier: Programming Language :: Python :: 3
Requires-Dist: azure-identity (>=1.25.1,<2.0.0)
Requires-Dist: azure-keyvault-secrets (>=4.10.0,<5.0.0)
Requires-Dist: azure-mgmt-cdn (>=13.1.1,<14.0.0)
Requires-Dist: azure-mgmt-resource (>=24.0.0,<25.0.0)
Requires-Dist: collectfasta (>=3.3.3,<4.0.0)
Requires-Dist: django (>=6.0,<7.0)
Requires-Dist: django-azure-communication-email (>=1.6.0,<2.0.0)
Requires-Dist: django-environ (>=0.12.0,<0.13.0)
Requires-Dist: django-redis (>=6.0.0,<7.0.0)
Requires-Dist: django-storages[azure] (>=1.14.6,<2.0.0)
Requires-Dist: django-tasks[rq] (>=0.9.0,<0.11.0)
Requires-Dist: psycopg-binary (>=3.3.2,<4.0.0) ; sys_platform == "win32"
Requires-Dist: psycopg[c] (>=3.3.2,<4.0.0) ; sys_platform == "linux"
Requires-Dist: pulumi (>=3.214.0)
Requires-Dist: pulumi-azure (>=6.31.0,<7.0.0)
Requires-Dist: pulumi-azure-native (>=3.12.0)
Requires-Dist: pulumi-random (>=4.18.5)
Requires-Dist: redis[hiredis] (>=7.1.0,<8.0.0)
Requires-Dist: tenacity (>=9.1.2,<10.0.0)
Project-URL: Homepage, https://gitlab.com/MaartenUreel/pulumi-django-azure
